cufile/__init__.py
cufile/bindings.py
cufile/cufile.py
tests/__init__.py
tests/test_cufile.py
cufile_python-0.2.0.dist-info/METADATA
cufile_python-0.2.0.dist-info/WHEEL
cufile_python-0.2.0.dist-info/top_level.txt
cufile_python-0.2.0.dist-info/RECORD
