Metadata-Version: 2.4
Name: cufile-python
Version: 0.2.0
Summary: A basic Python wrapper for the NVidia cuFile API
Home-page: https://github.com/yanok/cufile-python
Author: Ilya Yanok
Author-email: ilya.yanok@gmail.com
License: MIT
Classifier: Programming Language :: Python :: 3
Classifier: Operating System :: POSIX :: Linux
Requires-Python: >=3.6
Dynamic: author
Dynamic: author-email
Dynamic: classifier
Dynamic: description
Dynamic: description-content-type
Dynamic: home-page
Dynamic: license
Dynamic: requires-python
Dynamic: summary
